event_studies/__init__.py
event_studies/models/__init__.py
event_studies/models/linear_models.py
event_studies/models/finance/__init__.py
event_studies/models/finance/market_model.py
event_studies/models/finance/tests.py
event_studies-0.1.4.dist-info/LICENSE
event_studies-0.1.4.dist-info/METADATA
event_studies-0.1.4.dist-info/WHEEL
event_studies-0.1.4.dist-info/top_level.txt
event_studies-0.1.4.dist-info/RECORD
