Metadata-Version: 2.1
Name: event-studies
Version: 0.1.4
Summary: Useful code to conduct event studies
Home-page: https://github.com/taurusongithub/event-studies
Author: Nicolás Agustín Rodriguez Castro
Author-email: nicorodc@gmail.com
Project-URL: Bug Tracker, https://github.com/taurusongithub/event-studies/issues
Classifier: Programming Language :: Python :: 3
Classifier: License :: OSI Approved :: MIT License
Classifier: Operating System :: OS Independent
Requires-Python: >=3
License-File: LICENSE
Requires-Dist: pandas (>=1.0.0)
